vvv_vra/__init__.py
vvv_vra/schema/__init__.py
vvv_vra/schema/about.py
vvv_vra/schema/blueprint.py
vvv_vra/schema/catalog.py
vvv_vra/schema/deployment.py
vvv_vra/schema/gateway.py
vvv_vra/schema/policy.py
vvv_vra/schema/iaas/__init__.py
vvv_vra/schema/iaas/abstract.py
vvv_vra/schema/iaas/cloud.py
vvv_vra/schema/iaas/compute.py
vvv_vra/schema/iaas/flavor.py
vvv_vra/schema/iaas/image.py
vvv_vra/schema/iaas/loadbalance.py
vvv_vra/schema/iaas/network.py
vvv_vra/schema/iaas/storage.py
vvv_vra-0.1.3.dist-info/LICENSE
vvv_vra-0.1.3.dist-info/METADATA
vvv_vra-0.1.3.dist-info/WHEEL
vvv_vra-0.1.3.dist-info/top_level.txt
vvv_vra-0.1.3.dist-info/RECORD
