Metadata-Version: 2.1
Name: vvv-vra
Version: 0.1.3
Summary: VMware vRealize Automation Python SDK (based event driven<gevent>)
Home-page: https://github.com/HyechurnJang/vvv_vra
Author: Hyechurn Jang
Author-email: jangh@vmware.com
License: Apache 2.0
Platform: UNKNOWN
Classifier: License :: OSI Approved :: Apache Software License
Classifier: Topic :: Software Development :: Libraries :: Python Modules
Classifier: Programming Language :: Python :: 3
Requires-Dist: pygics
